asbdgsa/abc.py
asbdgsa-0.1.dist-info/METADATA
asbdgsa-0.1.dist-info/WHEEL
asbdgsa-0.1.dist-info/top_level.txt
asbdgsa-0.1.dist-info/RECORD
