Metadata-Version: 2.1
Name: asbdgsa
Version: 0.1
Summary: asbdgsa
Home-page: https://github.com/
Author: xx
Author-email: xxx@gmail.com
License: MIT
Keywords: asbdgsa
Platform: UNKNOWN
Classifier: Programming Language :: Python :: 3
Classifier: License :: OSI Approved :: MIT License
Requires-Python: >=2.7
